myne/__init__.py
myne/__init__.pyi
myne/myne.cpython-313-x86_64-linux-gnu.so
myne/py.typed
myne-0.3.0.dist-info/METADATA
myne-0.3.0.dist-info/WHEEL
myne-0.3.0.dist-info/entry_points.txt
myne-0.3.0.dist-info/RECORD
myne-0.3.0.dist-info/licenses/LICENSE-APACHE
myne-0.3.0.dist-info/licenses/LICENSE-MIT
